xcfont/__init__.py
xcfont/cli.py
xcfont-0.1.0.dist-info/WHEEL
xcfont-0.1.0.dist-info/METADATA
xcfont-0.1.0.dist-info/RECORD
