Metadata-Version: 2.1
Name: xcfont
Version: 0.1.0
Summary: 
Author: son.le
Author-email: anhsonleit@gmail.com
Requires-Python: >=3.7,<4.0
Classifier: Programming Language :: Python :: 3
Classifier: Programming Language :: Python :: 3.7
Classifier: Programming Language :: Python :: 3.8
Classifier: Programming Language :: Python :: 3.9
Requires-Dist: click (>=8.0.1,<9.0.0)
Requires-Dist: fonttools (>=4.24.4,<5.0.0)
Requires-Dist: funcy (>=1.16,<2.0)
